snsynth/__init__.py
snsynth/aggregate_seeded/__init__.py
snsynth/aggregate_seeded/aggregate_seeded.py
snsynth/aim/__init__.py
snsynth/aim/aim.py
snsynth/base.py
snsynth/definitions.py
snsynth/models/__init__.py
snsynth/models/dp_covariance.py
snsynth/models/linear_regression.py
snsynth/mst/LICENSE
snsynth/mst/__init__.py
snsynth/mst/mst.py
snsynth/mst/test-domain.json
snsynth/mwem.py
snsynth/pytorch/__init__.py
snsynth/pytorch/nn/__init__.py
snsynth/pytorch/nn/_discriminator.py
snsynth/pytorch/nn/_generator.py
snsynth/pytorch/nn/ctgan/LICENSE
snsynth/pytorch/nn/ctgan/base.py
snsynth/pytorch/nn/ctgan/ctgan.py
snsynth/pytorch/nn/ctgan/data_sampler.py
snsynth/pytorch/nn/dpctgan.py
snsynth/pytorch/nn/dpgan.py
snsynth/pytorch/nn/patectgan.py
snsynth/pytorch/nn/pategan.py
snsynth/pytorch/nn/privacy_utils.py
snsynth/pytorch/pytorch_synthesizer.py
snsynth/quail.py
snsynth/transform/__init__.py
snsynth/transform/anonymization.py
snsynth/transform/base.py
snsynth/transform/bin.py
snsynth/transform/chain.py
snsynth/transform/clamp.py
snsynth/transform/datetime.py
snsynth/transform/definitions.py
snsynth/transform/drop.py
snsynth/transform/identity.py
snsynth/transform/label.py
snsynth/transform/log.py
snsynth/transform/minmax.py
snsynth/transform/onehot.py
snsynth/transform/standard.py
snsynth/transform/table.py
snsynth/transform/type_map.py
snsynth/utils.py
smartnoise_synth-1.0.5.dist-info/METADATA
smartnoise_synth-1.0.5.dist-info/WHEEL
smartnoise_synth-1.0.5.dist-info/RECORD
