Metadata-Version: 2.3
Name: smartnoise-synth
Version: 1.0.5
Summary: Differentially Private Synthetic Data
License: MIT
Author: SmartNoise Team
Author-email: smartnoise@opendp.org
Requires-Python: >=3.9,<3.13
Classifier: License :: OSI Approved :: MIT License
Classifier: Programming Language :: Python :: 3
Classifier: Programming Language :: Python :: 3.9
Classifier: Programming Language :: Python :: 3.10
Classifier: Programming Language :: Python :: 3.11
Classifier: Programming Language :: Python :: 3.12
Requires-Dist: Faker (>=17.0.0)
Requires-Dist: opacus (>=0.14.0,<0.15.0)
Requires-Dist: pac-synth (>=0.0.8,<0.0.9)
Requires-Dist: smartnoise-sql (>=1.0.5,<2.0.0)
Requires-Dist: torch (>=2.2.0)
Project-URL: Homepage, https://smartnoise.org
Project-URL: Repository, https://github.com/opendp/smartnoise-sdk
